CIMtools/__init__.py
CIMtools/base.py
CIMtools/conditions_container.py
CIMtools/exceptions.py
CIMtools/metric_constants.py
CIMtools/utils.py
CIMtools/applicability_domain/__init__.py
CIMtools/applicability_domain/bounding_box.py
CIMtools/applicability_domain/leverage.py
CIMtools/applicability_domain/reaction_type_control.py
CIMtools/applicability_domain/similarity_distance.py
CIMtools/datasets/__init__.py
CIMtools/datasets/molconvert_chemaxon.py
CIMtools/metrics/__init__.py
CIMtools/metrics/applicability_domain_metrics.py
CIMtools/metrics/pairwise.py
CIMtools/model_selection/__init__.py
CIMtools/model_selection/group_out.py
CIMtools/model_selection/transformation_out.py
CIMtools/pipeline/__init__.py
CIMtools/pipeline/filter.py
CIMtools/preprocessing/__init__.py
CIMtools/preprocessing/cgr.py
CIMtools/preprocessing/equation.py
CIMtools/preprocessing/fragmentor.py
CIMtools/preprocessing/solvent.py
CIMtools/preprocessing/standardize/__init__.py
CIMtools/preprocessing/standardize/cgr.py
CIMtools/preprocessing/standardize/chemaxon.py
CIMtools-3.1.0.dist-info/LICENSE
CIMtools-3.1.0.dist-info/METADATA
CIMtools-3.1.0.dist-info/WHEEL
CIMtools-3.1.0.dist-info/top_level.txt
CIMtools-3.1.0.dist-info/zip-safe
CIMtools-3.1.0.dist-info/RECORD
